aibolit/__init__.py
aibolit/__main__.py
aibolit/config.py
aibolit/types_decl.py
aibolit/__pycache__/__init__.cpython-312.pyc
aibolit/__pycache__/__main__.cpython-312.pyc
aibolit/__pycache__/config.cpython-312.pyc
aibolit/__pycache__/types_decl.cpython-312.pyc
aibolit/ast_framework/__init__.py
aibolit/ast_framework/_auxiliary_data.py
aibolit/ast_framework/ast.py
aibolit/ast_framework/ast_node.py
aibolit/ast_framework/ast_node_type.py
aibolit/ast_framework/computed_fields_registry.py
aibolit/ast_framework/java_class.py
aibolit/ast_framework/java_class_decomposition.py
aibolit/ast_framework/java_class_field.py
aibolit/ast_framework/java_class_method.py
aibolit/ast_framework/java_package.py
aibolit/ast_framework/scope.py
aibolit/ast_framework/scope_extractors.py
aibolit/ast_framework/__pycache__/__init__.cpython-312.pyc
aibolit/ast_framework/__pycache__/_auxiliary_data.cpython-312.pyc
aibolit/ast_framework/__pycache__/ast.cpython-312.pyc
aibolit/ast_framework/__pycache__/ast_node.cpython-312.pyc
aibolit/ast_framework/__pycache__/ast_node_type.cpython-312.pyc
aibolit/ast_framework/__pycache__/computed_fields_registry.cpython-312.pyc
aibolit/ast_framework/__pycache__/java_class.cpython-312.pyc
aibolit/ast_framework/__pycache__/java_class_decomposition.cpython-312.pyc
aibolit/ast_framework/__pycache__/java_class_field.cpython-312.pyc
aibolit/ast_framework/__pycache__/java_class_method.cpython-312.pyc
aibolit/ast_framework/__pycache__/java_package.cpython-312.pyc
aibolit/ast_framework/__pycache__/scope.cpython-312.pyc
aibolit/ast_framework/__pycache__/scope_extractors.cpython-312.pyc
aibolit/ast_framework/computed_fields_catalog/__init__.py
aibolit/ast_framework/computed_fields_catalog/chained_fields.py
aibolit/ast_framework/computed_fields_catalog/nodes_filter.py
aibolit/ast_framework/computed_fields_catalog/standard_fields.py
aibolit/ast_framework/computed_fields_catalog/__pycache__/__init__.cpython-312.pyc
aibolit-1.3.0.dist-info/licenses/LICENSE.txt
aibolit-1.3.0.dist-info/METADATA
aibolit-1.3.0.dist-info/WHEEL
aibolit-1.3.0.dist-info/entry_points.txt
aibolit-1.3.0.dist-info/top_level.txt
aibolit-1.3.0.dist-info/RECORD
