Metadata-Version: 2.4
Name: aibolit
Version: 1.3.0
Summary: Aibolit: Static Analyzer with Machine Learning in Mind
Home-page: https://github.com/yegor256/aibolit
Download-URL: https://github.com/yegor256/aibolit
Author: Yegor Bugayenko
Author-email: yegor256@gmail.com
License: MIT
Classifier: Programming Language :: Python
Classifier: Environment :: Console
Classifier: Intended Audience :: Developers
Classifier: License :: OSI Approved :: MIT License
Classifier: Topic :: Software Development
Classifier: Topic :: Utilities
License-File: LICENSE.txt
Requires-Dist: beautifulsoup4==4.8.2
Requires-Dist: bs4==0.0.1
Requires-Dist: cached-property==1.2.0
Requires-Dist: catboost==1.2.8
Requires-Dist: chardet>=5.0.0
Requires-Dist: codecov==2.1.13
Requires-Dist: coverage==5.0.3
Requires-Dist: deprecated==1.2.10
Requires-Dist: flake8==7.2.0
Requires-Dist: javalang==0.13.0
Requires-Dist: lxml==5.4.0
Requires-Dist: matplotlib==3.10.3
Requires-Dist: mypy>=1.0.0
Requires-Dist: networkx==3.2
Requires-Dist: numpy==2.2.5
Requires-Dist: packaging>=23.0
Requires-Dist: pandas==2.2.3
Requires-Dist: pebble==4.5.3
Requires-Dist: pylint==3.3.7
Requires-Dist: scikit-learn==1.6.1
Requires-Dist: scipy==1.15.3
Requires-Dist: setuptools==80.7.1
Requires-Dist: sphinx==8.2.3
Requires-Dist: tqdm==4.32.1
Dynamic: author
Dynamic: author-email
Dynamic: classifier
Dynamic: description
Dynamic: download-url
Dynamic: home-page
Dynamic: license
Dynamic: license-file
Dynamic: requires-dist
Dynamic: summary
